[
  {
    "Id": "55713341-29ec-461d-9427-92b7b3f58d78",
    "Title": "Scream 6",
    "Year": "2023",
    "Released": "12 Apr 2023",
    "Runtime": "135 min",
    "Genre": "Horror, Thriller, Detective",
    "Director": "Matthew Bettinelli",
    "Writer": "Michael Bronner, Adam Patterson, Declan Lawn",
    "Actors": "James Norton, Matthew Douglas, Rob Malone",
    "Plot": "Sam, Tara, Chad and Mindy leave their hometown of Woodsboro to start over as four young people move to New York. But even there, the past does not leave them - once again, the mysterious killer in the Ghostface costume begins his bloody hunt.",
    "Language": "English",
    "Country": "United Kingdom",
    "Awards": "N/A",
    "Poster": "..\\..\\/Images/MoviePosters/Scream6Movie.jpg",
    "ImdbRating": "6.3",
    "Price": "6.00",
    "Subtitle": "Azerbaijani",
    "Session": {
      "Id": "600c25c3-f522-499d-b63d-6b464556daa2",
      "Cinema": "Sumgait Mall",
      "Hall": "Hall 11",
      "Date": "4/6/2023 12:00:00 AM",
      "Time": "23:30:00",
      "Price": "6.00"
    },
    "BusySeats": [
      81,
      86,
      4,
      6,
      21,
      72,
      19,
      26,
      38,
      42,
      75,
      12
    ]
  },
  {
    "Id": "8999287c-b3c0-4acf-b216-b94546906cbd",
    "Title": "John Wick 4",
    "Year": "2023",
    "Released": "26 04 2023",
    "Runtime": "190 min",
    "Genre": "Action, Thriller, Criminal",
    "Director": "Chad Stakhelski",
    "Writer": "Chad Stakhelski",
    "Actors": "Keanu Reeves, Donnie Yen, Bill Skarsgård",
    "Plot": "John Wick uncovers a path to defeating the High Table, but before he can earn his freedom, Wick must face off against a new enemy with powerful alliances across the globe and forces that turn old friends into new foes.",
    "Language": "English",
    "Country": "United States",
    "Awards": "N/A",
    "Poster": "..\\..\\/Images/MoviePosters/johnWickMovie.jpg",
    "ImdbRating": "8",
    "Price": "8.00",
    "Subtitle": "Azerbaijani",
    "Session": {
      "Id": "c3a6917d-9617-4be9-b120-fd112358c0e1",
      "Cinema": "Sumgait Mall",
      "Hall": "Hall 11",
      "Date": "4/3/2023 12:00:00 AM",
      "Time": "23:30:00",
      "Price": "8.00"
    },
    "BusySeats": [
      8,
      38,
      77,
      84,
      2,
      76,
      5,
      52,
      13,
      60,
      73,
      59,
      33,
      80,
      32,
      85,
      17,
      18,
      37,
      40,
      72,
      83,
      1,
      46,
      26,
      87,
      68,
      30,
      88,
      11,
      4,
      79,
      82,
      22,
      34,
      39,
      58,
      48,
      9,
      70,
      25
    ]
  },
  {
    "Id": "9432b611-0194-40b0-8044-5788df10d20b",
    "Title": "65",
    "Year": "2023",
    "Released": "12 APR 2023",
    "Runtime": "N/A",
    "Genre": "Fantasy, Action",
    "Director": "Scott Beck, Bryan Woods",
    "Writer": "Ian Brennan, Ryan Murphy",
    "Actors": "Adam Driver, Ariana Greenblatt, Chloe Coleman",
    "Plot": "After a crash on an unknown planet, pilot Mills quickly discovers that he's actually stuck on Earth... 65 million years ago. Now, with only one chance to escape, Mills and the last surviving Koa must make their way through an unknown area infested with dangerous creatures.",
    "Language": "English",
    "Country": "United States",
    "Awards": "N/A",
    "Poster": "/Images/MoviePosters/65Movie.jpg",
    "ImdbRating": "8.4",
    "Price": "9.00",
    "Subtitle": "Turkish",
    "Session": {
      "Id": "c13edf8f-9299-46f5-8da3-6e48665de9e4",
      "Cinema": "Sumgait Mall",
      "Hall": "Hall 11",
      "Date": "4/2/2023 12:00:00 AM",
      "Time": "19:55:00",
      "Price": "9.00"
    },
    "BusySeats": [
      29,
      5,
      1,
      0,
      70,
      55,
      36,
      54,
      83,
      48,
      87,
      28,
      41,
      86,
      33,
      2,
      49,
      61,
      32,
      16,
      79,
      68,
      77,
      78,
      25,
      19,
      66,
      43,
      90,
      82,
      69,
      46,
      73,
      74,
      39,
      9,
      52,
      72,
      18,
      58,
      63
    ]
  },
  {
    "Id": "ff1d56dc-d9fd-45aa-8536-4ff05cf46bd1",
    "Title": "Time Traveler",
    "Year": "2023",
    "Released": "19 Mar 2023",
    "Runtime": "135 min",
    "Genre": "Drama, Melodrama",
    "Director": " Olivier Traner",
    "Writer": "Matt Reeves, Peter Craig, Bob Kane",
    "Actors": "Lou de Laage, Rafael Personas, Isabelle Carré",
    "Plot": "Paris, 2052. Julia travels through her life in search of events that changed her fate. Sometimes it's something big, like a national music competition, and sometimes it's something as small as a passport left at home. A trifle that, years later, ruins your entire career and life.",
    "Language": "French",
    "Country": "France",
    "Awards": "N/A",
    "Poster": "/Images/MoviePosters/timeTravelerMovie.png",
    "ImdbRating": "7.9",
    "Price": "8.00",
    "Subtitle": "Azerbaijani",
    "Session": {
      "Id": "d0047806-425b-4fa5-852e-2bc0b51317c7",
      "Cinema": "Sumgait Mall",
      "Hall": "Hall 11",
      "Date": "4/2/2023 12:00:00 AM",
      "Time": "16:10:00",
      "Price": "8.00"
    },
    "BusySeats": [
      29,
      28,
      9,
      60,
      4,
      33,
      18,
      50,
      2,
      24,
      79,
      77,
      86,
      68,
      70,
      16,
      3,
      25,
      42,
      48,
      34,
      26,
      56,
      7,
      0,
      88,
      44,
      17,
      65,
      69,
      43,
      27,
      39,
      84,
      6
    ]
  },
  {
    "Id": "c8e3dd58-b6ff-4fb0-895c-889193031923",
    "Title": "The Shazam",
    "Year": "2023",
    "Released": "24 Mar 1972",
    "Runtime": "145 min",
    "Genre": "Fantasy, Action",
    "Director": "David F. Sandberg",
    "Writer": "David F. Sandberg , Mario",
    "Actors": "Diedrich Bader, Zachary Levi, Grays Fulton",
    "Plot": "The continuation of the adventures of a teenager who, at critical moments, with the help of a magic word, can turn into a superhero.",
    "Language": "English",
    "Country": "United States",
    "Awards": "None",
    "Poster": "..\\..\\/Images/MoviePosters/ShazamMovie.jpg",
    "ImdbRating": "7.2",
    "Price": "7.00",
    "Subtitle": "Azerbaijani",
    "Session": {
      "Id": "9a83b934-dbb2-45a3-b216-1e7f64d94af0",
      "Cinema": "Sumgait Mall",
      "Hall": "Hall 11",
      "Date": "4/4/2023 12:00:00 AM",
      "Time": "21:15:00",
      "Price": "7.00"
    },
    "BusySeats": [
      45,
      33,
      3,
      57,
      12,
      61,
      37,
      2,
      52,
      42,
      51,
      24,
      4,
      34,
      59,
      20,
      89,
      65,
      88,
      16,
      54,
      26,
      15,
      39,
      30,
      1,
      71,
      17,
      43,
      10,
      13,
      7,
      41,
      27,
      67,
      60,
      35,
      5,
      87,
      79,
      55,
      48,
      21,
      70,
      23
    ]
  },
  {
    "Id": "fedd6bbd-e655-400f-983a-d5e1bf24f6e4",
    "Title": "Zəhər Tuluğu ",
    "Year": "2023",
    "Released": "12 avg 2021",
    "Runtime": "115 min",
    "Genre": "Comedy",
    "Director": "Orkhan Mardan",
    "Writer": "Taleh Yuzbayov",
    "Actors": "Nezaket Heyderova, Rasim Jafarov, Shaban Imkani, Taleh Yuzbayov, Leman Merrih",
    "Plot": "Adil continues his journey in cinema. There are two lines about Adil's life. One of them is modern day, which Adil try to save pregnant Leyla's child from abortion, and another one is about past of Adil.",
    "Language": "Azerbaijani",
    "Country": "Azerbaijan",
    "Awards": "None",
    "Poster": "..\\..\\/Images/MoviePosters/ZaharTulugu.jpg",
    "ImdbRating": "6",
    "Price": "6.00",
    "Subtitle": "Azerbaijani",
    "Session": {
      "Id": "2e1a71a9-79a4-4679-8b14-1c420c006adc",
      "Cinema": "Sumgait Mall",
      "Hall": "Hall 11",
      "Date": "4/3/2023 12:00:00 AM",
      "Time": "19:40:00",
      "Price": "6.00"
    },
    "BusySeats": [
      10,
      33,
      79,
      21,
      78,
      84,
      24,
      71,
      25,
      74,
      29,
      13,
      36,
      85,
      8,
      43,
      90
    ]
  },
  {
    "Id": "2dab65b8-dc6e-464f-9816-d43ee8f1a8bc",
    "Title": "Puss In Boots 2 - The Last Wish",
    "Year": "2023",
    "Released": "29 Feb 2023",
    "Runtime": "115 min",
    "Genre": "Cartoon, Comedy, Adventure",
    "Director": "Joel Crawford, Hanuel Mercado",
    "Writer": "Richard Claus, Brian Cleveland, Jason Cleveland",
    "Actors": "Joel Crawford, Hanuel Mercado",
    "Plot": "Everyone's favorite bold, fearless and such a touching cat is back! Puss in Boots has spent eight of his nine lives and is now embarking on a new adventure! The charismatic rogue, accompanied by the adorable Kitty Softpaws and the chatty dog Perro, embark on an epic journey to find the mythical Wishing Star and see if cats really only have 9 lives... or are there alternatives?",
    "Language": "English",
    "Country": "United States",
    "Awards": "1 win",
    "Poster": "/Images/MoviePosters/KotMovie.jpg",
    "ImdbRating": "4.8",
    "Price": "5.00",
    "Subtitle": "Azerbaijani",
    "Session": {
      "Id": "7e17dd23-c9e7-40e4-95e7-1db43294abc7",
      "Cinema": "Sumgait Mall",
      "Hall": "Hall 11",
      "Date": "4/6/2023 12:00:00 AM",
      "Time": "17:55:00",
      "Price": "5.00"
    },
    "BusySeats": [
      87,
      8,
      63,
      41,
      11,
      62,
      82,
      65,
      56,
      2,
      64,
      27,
      74,
      68,
      54,
      10,
      32,
      47,
      75,
      15,
      29,
      37,
      61,
      24,
      57,
      23,
      50,
      25,
      70,
      21,
      73,
      59,
      33,
      19,
      18,
      58,
      45,
      79,
      77,
      90,
      30,
      78,
      26,
      4,
      13,
      49,
      89,
      72,
      53,
      28,
      69,
      43
    ]
  },
  {
    "Id": "b4822912-7d36-4bb8-88b6-a4df84195e2e",
    "Title": "Avatar The Way Of Water",
    "Year": "2023",
    "Released": "24 Sep 2023",
    "Runtime": "210 min",
    "Genre": "Fantasy, Action, Thriller",
    "Director": "James Cameron",
    "Writer": "Mitchell Burgess, Robin Green",
    "Actors": "Mishel Yeo, Zoi Saldana, Keyt Uinslet",
    "Plot": "Jake Sully lives with his newfound family formed on the planet of Pandora. Once a familiar threat returns to finish what was previously started, Jake must work with Neytiri and the army of the Na'vi race to protect their planet",
    "Language": "English",
    "Country": "United States",
    "Awards": "Nominated for 1 Primetime Emmy. 4 wins & 16 nominations total",
    "Poster": "/Images/MoviePosters/Avatar2Movie.jpg",
    "ImdbRating": "8.5",
    "Price": "9.00",
    "Subtitle": "Azerbaijani",
    "Session": {
      "Id": "9a594bd5-0b0a-4c77-8d27-0a79d0cb870c",
      "Cinema": "Sumgait Mall",
      "Hall": "Hall 11",
      "Date": "4/4/2023 12:00:00 AM",
      "Time": "16:45:00",
      "Price": "9.00"
    },
    "BusySeats": [
      69,
      43,
      49,
      64,
      25,
      39,
      34,
      47,
      77,
      12,
      68,
      84,
      53,
      31,
      48,
      32,
      66,
      67,
      51,
      26,
      63,
      23,
      1,
      21,
      20,
      13,
      74,
      9,
      11,
      62,
      71,
      45,
      0,
      40,
      52,
      89,
      86,
      41,
      50,
      75,
      33,
      85,
      37,
      18,
      57,
      83,
      5,
      4,
      6,
      7,
      30,
      8,
      14,
      15,
      72,
      42,
      70
    ]
  },
  {
    "Id": "76673269-f1d0-4f57-a3ca-248f01a80799",
    "Title": "Hayaller Ülkesi",
    "Year": "2023",
    "Released": "18 Dec 2023",
    "Runtime": "105 min",
    "Genre": "Cartoon, Family",
    "Director": "Ricard Cussó",
    "Writer": "Ricard Cussó",
    "Actors": "Miranda Tapsell, Ross Noble, Kate Murphy",
    "Plot": "Little opossum Kerry dreams of celebrating Christmas with snow, because this is what creates a real holiday spirit, a cozy atmosphere and indescribable children's delight! Fortunately, there is a Tree nearby that can fulfill wishes. You just need to find a flower and say what you want. Everything is very simple, but something went wrong - and everything around froze, and the Tree itself was dying. Now Kerry must, by all means, correct what she has done.",
    "Language": "Turkish",
    "Country": "Turkey",
    "Awards": "N/A",
    "Poster": "/Images/MoviePosters/hayeller-ulkesiMovie.jpg",
    "ImdbRating": "9",
    "Price": "9.00",
    "Subtitle": "Azerbaijani",
    "Session": {
      "Id": "c816e46c-b48c-4d4f-89cf-ad88d9ac7197",
      "Cinema": "Sumgait Mall",
      "Hall": "Hall 11",
      "Date": "4/7/2023 12:00:00 AM",
      "Time": "21:00:00",
      "Price": "9.00"
    },
    "BusySeats": [
      7,
      5,
      79,
      22,
      86,
      90,
      80,
      18,
      30,
      68,
      34,
      55,
      44,
      61,
      39,
      3,
      76,
      51,
      85,
      0,
      43,
      11,
      83,
      81,
      59,
      20,
      58,
      46,
      41,
      75,
      89,
      69,
      25,
      35,
      9,
      24,
      78,
      37,
      63,
      12,
      71,
      16,
      88,
      66,
      23
    ]
  },
  {
    "Id": "0f0b4706-899b-4248-836f-86727898a06a",
    "Title": "Jin's Look",
    "Year": "2023",
    "Released": "05 Apr 2023",
    "Runtime": "85 min",
    "Genre": "Horror",
    "Director": "Burak Kuchuk",
    "Writer": "Burak Kuchuk",
    "Actors": "Burak Kuchuk, Seyhan Chakaloghlu, Sila Ildemlik",
    "Plot": "'Jin's Look'is based on a cold-blooded incident that began in the village of Kanlybel. Kind and beloved by all Karim, falls in love with someone who should not be loved, and does many things to achieve his goal. There are many disputes between the family of Karim and the girl and forbidden rites are performed. Now Karim himself must reveal this mystical story.",
    "Language": "Turkish",
    "Country": "Turkey",
    "Awards": "N/A",
    "Poster": "/Images/MoviePosters/cinSuretiMovie.jpg",
    "ImdbRating": "6.4",
    "Price": "7.00",
    "Subtitle": "Turkish",
    "Session": {
      "Id": "a78fa898-3bbf-4577-9949-cb223b9017c5",
      "Cinema": "Sumgait Mall",
      "Hall": "Hall 11",
      "Date": "4/5/2023 12:00:00 AM",
      "Time": "20:35:00",
      "Price": "7.00"
    },
    "BusySeats": [
      70,
      7,
      53,
      67,
      30,
      4,
      59,
      51,
      75,
      26,
      23,
      20,
      86,
      77,
      43,
      36,
      54,
      60
    ]
  },
  {
    "Id": "e01472f0-f4e5-4205-9e5c-966b9cc5c040",
    "Title": "Ant Man And The Wasp Quantumania",
    "Year": "2023",
    "Released": "02 Mar 2023",
    "Runtime": "140 min",
    "Genre": "Fantasy, Action, Thriller, Adventure",
    "Director": "Payton Reid",
    "Writer": "Nikolaj Coster-Waldau, Joe Derrick, Ejnar Mikkelsen",
    "Actors": "Michelle Pfeiffer, Evangeline Lilly, Paul Rudd",
    "Plot": "About the adventures of former petty criminal Scott Lang, who became the owner of a suit that allows you to shrink and grow in size. Together with his partner Hope van Dyne, the daughter of the famous physicist and entomologist Hank Pym, who developed the Ant-Man costume, Scott once again saves the world from an impending threat.",
    "Language": "Danish",
    "Country": "Denmark",
    "Awards": "N/A",
    "Poster": "/Images/MoviePosters/antman3Movie.jpg",
    "ImdbRating": "8",
    "Price": "8.00",
    "Subtitle": "Azerbaijani",
    "Session": {
      "Id": "5c861059-7579-4a1b-8d91-08aad8e5deaf",
      "Cinema": "Sumgait Mall",
      "Hall": "Hall 11",
      "Date": "4/2/2023 12:00:00 AM",
      "Time": "13:40:00",
      "Price": "8.00"
    },
    "BusySeats": [
      10,
      43,
      22,
      82,
      66,
      72,
      70,
      59,
      62,
      38,
      49,
      45,
      30,
      69,
      63,
      2,
      40,
      83,
      76,
      7,
      26,
      9,
      85,
      46,
      28,
      50,
      78,
      36,
      53,
      41,
      14,
      4,
      89,
      37,
      88,
      86,
      24,
      12,
      67,
      52,
      58,
      21,
      68,
      20,
      81,
      16,
      27,
      11
    ]
  }
]